{"inn": "6027184758", "ogrn": "1176027010598", "companyName": "Общество с ограниченной ответственностью \"ОМНИКОММ АВТО-СЕВЕР\"", "companyShortName": "ООО \"ОМНИКОММ АВТО-СЕВЕР\"", "revenue2019": 25239000.0, "revenue2018": 18373000.0, "revenueGrowth": 6866000.0, "revenueGrowthPerc": 37.37, "purchasesWins": 2, "purchasesTotal": 18, "purchasesLost": 36, "revenueLost": 2284183.26, "bgOverpaymentPerc": 34.72, "contractsSum": 126899.07, "competitor": {"inn": "3328477520", "ogrn": "1113328009035", "companyName": "Общество с ограниченной ответственностью \"АльфаВладТелематика\"", "companyShortName": "ООО \"АВТ\"", "revenueGrowthPerc": 5.27, "purchasesWins": 14, "purchasesTotal": 201, "bgSavingEconomy": 1508.3825952000002, "contractsSum": 1571231.87}}